cookies_converter/__init__.py
cookies_converter/cookie_data.py
cookies_converter/cookies_converter.py
cookies_converter/json_cookies/__init__.py
cookies_converter/json_cookies/json_cookies.py
cookies_converter/netscape_cookies/__init__.py
cookies_converter/netscape_cookies/netscape_cookies.py
cookies_converter-1.0.1.dist-info/METADATA
cookies_converter-1.0.1.dist-info/WHEEL
cookies_converter-1.0.1.dist-info/top_level.txt
cookies_converter-1.0.1.dist-info/RECORD
