Metadata-Version: 2.2
Name: cookies_converter
Version: 1.0.1
Summary: Cookies converter
Author-email: REDKLAUS <reallifestd@gmail.com>
Project-URL: Homepage, https://github.com/RedKlaus/cookies_converter
Project-URL: Issues, https://github.com/RedKlaus/cookies_converter/issues
Classifier: Programming Language :: Python :: 3
Classifier: License :: OSI Approved :: MIT License
Classifier: Operating System :: OS Independent
Requires-Python: ~=3.12
Requires-Dist: pydantic>=2.8.2
